README.md
setup.py
google_streetview/__init__.py
google_streetview/__main__.py
google_streetview/api.py
google_streetview/cli.py
google_streetview/config.json
google_streetview/helpers.py
google_streetview.egg-info/PKG-INFO
google_streetview.egg-info/SOURCES.txt
google_streetview.egg-info/dependency_links.txt
google_streetview.egg-info/entry_points.txt
google_streetview.egg-info/requires.txt
google_streetview.egg-info/top_level.txt