Metadata-Version: 2.1
Name: google-streetview
Version: 1.2.9
Summary: A command line tool and module for Google Street View Image API.
Home-page: https://github.com/rrwen/google_streetview
Author: Richard Wen
Author-email: rrwen.dev@gmail.com
License: MIT
Download-URL: https://github.com/rrwen/google_streetview/archive/master.zip
Keywords: google,api,street,view,streetview,image,map,address,location,road,route,city,panorama,photo,cli,command,line,interface,tool,module
Platform: UNKNOWN
